integration_test/__init__.py
integration_test/test_experiment.py
integration_test/test_hyperopt.py
integration_test/test_sigopt.py
integration_test/test_xgboost_experiment.py
integration_test/test_xgboost_run.py
sigopt/__init__.py
sigopt/aiexperiment_context.py
sigopt/compat.py
sigopt/config.py
sigopt/defaults.py
sigopt/endpoint.py
sigopt/exception.py
sigopt/factory.py
sigopt/file_utils.py
sigopt/interface.py
sigopt/lib.py
sigopt/local_run_context.py
sigopt/log_capture.py
sigopt/magics.py
sigopt/model_aware_run.py
sigopt/objects.py
sigopt/paths.py
sigopt/ratelimit.py
sigopt/request_driver.py
sigopt/resource.py
sigopt/run_context.py
sigopt/run_factory.py
sigopt/run_params.py
sigopt/sigopt_logging.py
sigopt/urllib3_patch.py
sigopt/utils.py
sigopt/version.py
sigopt/cli/__init__.py
sigopt/cli/__main__.py
sigopt/cli/utils.py
sigopt/cli/arguments/__init__.py
sigopt/cli/arguments/cluster_filename.py
sigopt/cli/arguments/cluster_name.py
sigopt/cli/arguments/commands.py
sigopt/cli/arguments/dockerfile.py
sigopt/cli/arguments/experiment_file.py
sigopt/cli/arguments/experiment_id.py
sigopt/cli/arguments/identifiers.py
sigopt/cli/arguments/load_yaml.py
sigopt/cli/arguments/project.py
sigopt/cli/arguments/provider.py
sigopt/cli/arguments/run_file.py
sigopt/cli/arguments/source_file.py
sigopt/cli/arguments/validate.py
sigopt/cli/commands/__init__.py
sigopt/cli/commands/base.py
sigopt/cli/commands/config.py
sigopt/cli/commands/init.py
sigopt/cli/commands/optimize_base.py
sigopt/cli/commands/run_base.py
sigopt/cli/commands/version.py
sigopt/cli/commands/cluster/__init__.py
sigopt/cli/commands/cluster/base.py
sigopt/cli/commands/cluster/clean.py
sigopt/cli/commands/cluster/connect.py
sigopt/cli/commands/cluster/create.py
sigopt/cli/commands/cluster/destroy.py
sigopt/cli/commands/cluster/disconnect.py
sigopt/cli/commands/cluster/install_plugins.py
sigopt/cli/commands/cluster/kubectl.py
sigopt/cli/commands/cluster/not_installed.py
sigopt/cli/commands/cluster/optimize.py
sigopt-8.8.3.dist-info/LICENSE
sigopt-8.8.3.dist-info/METADATA
sigopt-8.8.3.dist-info/WHEEL
sigopt-8.8.3.dist-info/entry_points.txt
sigopt-8.8.3.dist-info/top_level.txt
sigopt-8.8.3.dist-info/RECORD
